{
  "slug": "autonomous-vehicles",
  "document_number": "2026-01274",
  "title": "Notice and Request for Comment; Proposal for a New United Nations Global Technical Regulation on Automated Driving Systems (ADS)",
  "type": "Notice",
  "publication_date": "2026-01-23",
  "topic": "ai_safety",
  "file": "autonomous-vehicles.txt",
  "source": "Federal Register (federalregister.gov)",
  "url": "https://www.federalregister.gov/documents/2026/01/23/2026-01274/notice-and-request-for-comment-proposal-for-a-new-united-nations-global-technical-regulation-on",
  "license": "Public Domain (US Government)"
}